detectable991/__init__.py
detectable991/detectable991.py
detectable991-1.1.dist-info/METADATA
detectable991-1.1.dist-info/WHEEL
detectable991-1.1.dist-info/top_level.txt
detectable991-1.1.dist-info/RECORD
