Metadata-Version: 2.4
Name: detectable991
Version: 1.1
Summary: This is just a package
Author: Noman
Author-email: mnomanansari99@gmail.com
Requires-Python: >=3.6
Dynamic: author
Dynamic: author-email
Dynamic: requires-python
Dynamic: summary
